<annotation>
	<folder>Final </folder>
	<filename>914.jpg</filename>
	<path>/Users/najibseguias/OD Working/Final /914.jpg</path>
	<source>
		<database>Unknown</database>
	</source>
	<size>
		<width>800</width>
		<height>600</height>
		<depth>3</depth>
	</size>
	<segmented>0</segmented>
	<object>
		<name>glass</name>
		<pose>Unspecified</pose>
		<truncated>0</truncated>
		<difficult>0</difficult>
		<bndbox>
			<xmin>149</xmin>
			<ymin>97</ymin>
			<xmax>344</xmax>
			<ymax>229</ymax>
		</bndbox>
	</object>
</annotation>
